[
    {
        "itemName": "Fur Hoodie",
        "pricePerItem": "Rs. 910"
    },

    {
        "itemName": "Black Hoodie",
        "pricePerItem": "Rs. 900"
    },

    {
        "itemName": "Red Hoodie",
        "pricePerItem": "Rs. 840"
    },

    {
        "itemName": "Rainbow Hoodie",
        "pricePerItem": "Rs. 890"
    },

    {
        "itemName": "Cute Hoodie",
        "pricePerItem": "Rs. 850"
    },

    {
        "itemName": "Basic Hoodie",
        "pricePerItem": "Rs. 900"
    }
]